README.md
setup.py
service/__init__.py
service/version.py
service/client/__init__.py
service/server/__init__.py
service/server/benchmark.py
service/server/cli.py
service/server/helper.py
service/server/http_proxy.py
service/server/model.py
service/server/zmq_decor.py
text2vec_service.egg-info/PKG-INFO
text2vec_service.egg-info/SOURCES.txt
text2vec_service.egg-info/dependency_links.txt
text2vec_service.egg-info/entry_points.txt
text2vec_service.egg-info/not-zip-safe
text2vec_service.egg-info/requires.txt
text2vec_service.egg-info/top_level.txt