Metadata-Version: 2.1
Name: text2vec-service
Version: 0.0.5
Summary: Mapping a variable-length sentence to a fixed-length vector using BERT model (Server)
Home-page: https://github.com/shibing624/text2vec-service
Author: XuMing
Author-email: xuming624@qq.com
License: Apache 2.0
Keywords: bert,nlp,pytorch,machine learning,sentence encoding embedding serving
Platform: UNKNOWN
Classifier: Programming Language :: Python :: 3.6
Classifier: Programming Language :: Python :: 3.7
Classifier: Programming Language :: Python :: 3.8
Classifier: Programming Language :: Python :: 3.9
Classifier: License :: OSI Approved :: Apache Software License
Classifier: Operating System :: OS Independent
Classifier: Topic :: Scientific/Engineering :: Artificial Intelligence
Provides-Extra: pytorch
Provides-Extra: http
